{
	"name": "add liquidity",
	"steps": [
		{
			"step": "setState",
			"accounts": {
				"address:user": {
					"nonce": "2",
					"balance": "0",
					"esdt": {
						"str:ALC-abcdef": "3,000,000,000",
						"str:BLC-abcdef": "3,000,000,000"
					},
					"storage": {}
				},
				"address:another_user": {
					"nonce": "2",
					"balance": "0",
					"esdt": {
						"str:ALC-abcdef": "3,000,000,000",
						"str:BLC-abcdef": "3,000,000,000"
					},
					"storage": {}
				},
				"address:contract": {
					"nonce": "0",
					"balance": "0",
					"esdt": {
						"str:ALC-abcdef": "4,000,000,000",
						"str:BLC-abcdef": "4,000,000,000",
						"str:CLC-abcdef": "5,000,000,000"
					},
					"storage": {
						"str:token_a_name": "str:ALC-abcdef",
						"str:token_b_name": "str:BLC-abcdef",
						"str:lpTokenIdentifier": "str:CLC-abcdef",
						"0x66756e6473757365725f5f5f5f5f5f5f5f5f5f5f5f5f5f5f5f5f5f5f5f5f5f5f5f5f5f5f5f0000000a414c432d616263646566": "2,000,000,000",
						"0x66756e6473757365725f5f5f5f5f5f5f5f5f5f5f5f5f5f5f5f5f5f5f5f5f5f5f5f5f5f5f5f0000000a424c432d616263646566": "2,000,000,000",
						"0x66756e6473616e6f746865725f757365725f5f5f5f5f5f5f5f5f5f5f5f5f5f5f5f5f5f5f5f0000000a414c432d616263646566": "2,000,000,000",
						"0x66756e6473616e6f746865725f757365725f5f5f5f5f5f5f5f5f5f5f5f5f5f5f5f5f5f5f5f0000000a424c432d616263646566": "2,000,000,000"
					},
					"code": "file:../output/elrond_dex_pair.wasm"
				}
			}
		},
		{
			"step": "scCall",
			"txId": "add-liquidity",
			"tx": {
				"from": "address:user",
				"to": "address:contract",
				"value": "0",
				"function": "addLiquidity",
				"arguments": ["2,000,000,000", "2,000,000,000", "1,000,000,000", "1,000,000,000"],
				"gasLimit": "100,000,000",
				"gasPrice": "0"
			},
			"expect": {
				"status": "0",
				"message": "",
				"gas": "*",
				"refund": "*"
			}
		},
		{
			"step": "scCall",
			"txId": "add-liquidity",
			"tx": {
				"from": "address:another_user",
				"to": "address:contract",
				"value": "0",
				"function": "addLiquidity",
				"arguments": ["2,000,000,000", "2,000,000,000", "1,000,000,000", "1,000,000,000"],
				"gasLimit": "100,000,000",
				"gasPrice": "0"
			},
			"expect": {
				"status": "0",
				"message": "",
				"gas": "*",
				"refund": "*"
			}
		},
		{
			"step": "checkState",
			"accounts": {
				"address:user": {
					"nonce": "3",
					"balance": "0",
					"esdt": {
						"str:ALC-abcdef": "3,000,000,000",
						"str:BLC-abcdef": "3,000,000,000",
						"str:CLC-abcdef": "1,999,999,000"
					},
					"storage": {}
				},
				"address:another_user": {
					"nonce": "3",
					"balance": "0",
					"esdt": {
						"str:ALC-abcdef": "3,000,000,000",
						"str:BLC-abcdef": "3,000,000,000",
						"str:CLC-abcdef": "2,000,000,000"
					},
					"storage": {}
				},
				"address:contract": {
					"nonce": "0",
					"balance": "0",
					"esdt": {
						"str:ALC-abcdef": "4,000,000,000",
						"str:BLC-abcdef": "4,000,000,000",
						"str:CLC-abcdef": "1,000,001,000"
					},
					"storage": {
						"str:token_a_name": "str:ALC-abcdef",
						"str:token_b_name": "str:BLC-abcdef",
						"str:lpTokenIdentifier": "str:CLC-abcdef",
						"0x66756e6473757365725f5f5f5f5f5f5f5f5f5f5f5f5f5f5f5f5f5f5f5f5f5f5f5f5f5f5f5f0000000a414c432d616263646566": "0",
						"0x66756e6473757365725f5f5f5f5f5f5f5f5f5f5f5f5f5f5f5f5f5f5f5f5f5f5f5f5f5f5f5f0000000a424c432d616263646566": "0",
						"0x66756e6473616e6f746865725f757365725f5f5f5f5f5f5f5f5f5f5f5f5f5f5f5f5f5f5f5f0000000a414c432d616263646566": "0",
						"0x66756e6473616e6f746865725f757365725f5f5f5f5f5f5f5f5f5f5f5f5f5f5f5f5f5f5f5f0000000a424c432d616263646566": "0",
						"0x726573657276650000000a414c432d616263646566": "4,000,000,000",
						"0x726573657276650000000a424c432d616263646566": "4,000,000,000",
						"0x746f74616c5f737570706c79": "4,000,000,000"
					},
					"code": "file:../output/elrond_dex_pair.wasm"
				}
			}
		}
	]
}
